ostracker/__init__.py
ostracker/test_lib.py
ostracker2-0.0.9.dist-info/licenses/LICENSE
ostracker2-0.0.9.dist-info/METADATA
ostracker2-0.0.9.dist-info/WHEEL
ostracker2-0.0.9.dist-info/top_level.txt
ostracker2-0.0.9.dist-info/RECORD
